{
    "2to3": "/usr/local/bin/2to3",
    "2to3-3.10": "/usr/local/bin/2to3-3.10",
    "adig": "/usr/local/bin/adig",
    "ahost": "/usr/local/bin/ahost",
    "bunzip2": "/usr/local/bin/bunzip2",
    "bzcat": "/usr/local/bin/bzcat",
    "bzcmp": "/usr/local/bin/bzcmp",
    "bzdiff": "/usr/local/bin/bzdiff",
    "bzegrep": "/usr/local/bin/bzegrep",
    "bzfgrep": "/usr/local/bin/bzfgrep",
    "bzgrep": "/usr/local/bin/bzgrep",
    "bzip2": "/usr/local/bin/bzip2",
    "bzip2recover": "/usr/local/bin/bzip2recover",
    "bzless": "/usr/local/bin/bzless",
    "bzmore": "/usr/local/bin/bzmore",
    "c_rehash": "/usr/local/bin/c_rehash",
    "captoinfo": "/usr/local/bin/captoinfo",
    "clear": "/usr/local/bin/clear",
    "compile_et": "/usr/local/bin/compile_et",
    "curl-config": "/usr/local/bin/curl-config",
    "gss-client": "/usr/local/bin/gss-client",
    "idle3": "/usr/local/bin/idle3",
    "idle3.10": "/usr/local/bin/idle3.10",
    "infocmp": "/usr/local/bin/infocmp",
    "infotocap": "/usr/local/bin/infotocap",
    "k5srvutil": "/usr/local/bin/k5srvutil",
    "kadmin": "/usr/local/bin/kadmin",
    "kdestroy": "/usr/local/bin/kdestroy",
    "keyctl": "/usr/local/bin/keyctl",
    "kinit": "/usr/local/bin/kinit",
    "klist": "/usr/local/bin/klist",
    "kpasswd": "/usr/local/bin/kpasswd",
    "krb5-config": "/usr/local/bin/krb5-config",
    "ksu": "/usr/local/bin/ksu",
    "kswitch": "/usr/local/bin/kswitch",
    "ktutil": "/usr/local/bin/ktutil",
    "kvno": "/usr/local/bin/kvno",
    "libdeflate-gunzip": "/usr/local/bin/libdeflate-gunzip",
    "libdeflate-gzip": "/usr/local/bin/libdeflate-gzip",
    "ncurses6-config": "/usr/local/bin/ncurses6-config",
    "ncursesw6-config": "/usr/local/bin/ncursesw6-config",
    "nghttp": "/usr/local/bin/nghttp",
    "nghttpd": "/usr/local/bin/nghttpd",
    "nghttpx": "/usr/local/bin/nghttpx",
    "openssl": "/usr/local/bin/openssl",
    "pip": "/usr/local/bin/pip",
    "pip3": "/usr/local/bin/pip3",
    "py.test": "/usr/local/bin/py.test",
    "pydoc": "/usr/local/bin/pydoc",
    "pydoc3": "/usr/local/bin/pydoc3",
    "pydoc3.10": "/usr/local/bin/pydoc3.10",
    "pytest": "/usr/local/bin/pytest",
    "python": "/usr/local/bin/python",
    "python3": "/usr/local/bin/python3",
    "python3-config": "/usr/local/bin/python3-config",
    "python3.1": "/usr/local/bin/python3.1",
    "python3.10": "/usr/local/bin/python3.10",
    "python3.10-config": "/usr/local/bin/python3.10-config",
    "reset": "/usr/local/bin/reset",
    "sclient": "/usr/local/bin/sclient",
    "sim_client": "/usr/local/bin/sim_client",
    "sqlite3_analyzer": "/usr/local/bin/sqlite3_analyzer",
    "tabs": "/usr/local/bin/tabs",
    "tclsh": "/usr/local/bin/tclsh",
    "tclsh8.6": "/usr/local/bin/tclsh8.6",
    "tic": "/usr/local/bin/tic",
    "toe": "/usr/local/bin/toe",
    "tput": "/usr/local/bin/tput",
    "tset": "/usr/local/bin/tset",
    "unzstd": "/usr/local/bin/unzstd",
    "uuclient": "/usr/local/bin/uuclient",
    "wheel": "/usr/local/bin/wheel",
    "wish": "/usr/local/bin/wish",
    "wish8.6": "/usr/local/bin/wish8.6",
    "x86_64-conda-linux-gnu-ld": "/usr/local/bin/x86_64-conda-linux-gnu-ld",
    "x86_64-conda_cos6-linux-gnu-ld": "/usr/local/bin/x86_64-conda_cos6-linux-gnu-ld",
    "zstd": "/usr/local/bin/zstd",
    "zstdcat": "/usr/local/bin/zstdcat",
    "zstdgrep": "/usr/local/bin/zstdgrep",
    "zstdless": "/usr/local/bin/zstdless",
    "zstdmt": "/usr/local/bin/zstdmt"
}