{
    "2to3": "/usr/local/bin/2to3",
    "2to3-3.12": "/usr/local/bin/2to3-3.12",
    "adig": "/usr/local/bin/adig",
    "aggregate_profile.pl": "/usr/local/bin/aggregate_profile.pl",
    "ahost": "/usr/local/bin/ahost",
    "alimask": "/usr/local/bin/alimask",
    "aria2c": "/usr/local/bin/aria2c",
    "awk": "/usr/local/bin/awk",
    "bunzip2": "/usr/local/bin/bunzip2",
    "bzcat": "/usr/local/bin/bzcat",
    "bzcmp": "/usr/local/bin/bzcmp",
    "bzdiff": "/usr/local/bin/bzdiff",
    "bzegrep": "/usr/local/bin/bzegrep",
    "bzfgrep": "/usr/local/bin/bzfgrep",
    "bzgrep": "/usr/local/bin/bzgrep",
    "bzip2": "/usr/local/bin/bzip2",
    "bzip2recover": "/usr/local/bin/bzip2recover",
    "bzless": "/usr/local/bin/bzless",
    "bzmore": "/usr/local/bin/bzmore",
    "c_rehash": "/usr/local/bin/c_rehash",
    "captoinfo": "/usr/local/bin/captoinfo",
    "clear": "/usr/local/bin/clear",
    "derb": "/usr/local/bin/derb",
    "easel": "/usr/local/bin/easel",
    "esl-afetch": "/usr/local/bin/esl-afetch",
    "esl-alimanip": "/usr/local/bin/esl-alimanip",
    "esl-alimap": "/usr/local/bin/esl-alimap",
    "esl-alimask": "/usr/local/bin/esl-alimask",
    "esl-alimerge": "/usr/local/bin/esl-alimerge",
    "esl-alipid": "/usr/local/bin/esl-alipid",
    "esl-alirev": "/usr/local/bin/esl-alirev",
    "esl-alistat": "/usr/local/bin/esl-alistat",
    "esl-compalign": "/usr/local/bin/esl-compalign",
    "esl-compstruct": "/usr/local/bin/esl-compstruct",
    "esl-construct": "/usr/local/bin/esl-construct",
    "esl-histplot": "/usr/local/bin/esl-histplot",
    "esl-mask": "/usr/local/bin/esl-mask",
    "esl-mixdchlet": "/usr/local/bin/esl-mixdchlet",
    "esl-reformat": "/usr/local/bin/esl-reformat",
    "esl-selectn": "/usr/local/bin/esl-selectn",
    "esl-seqrange": "/usr/local/bin/esl-seqrange",
    "esl-seqstat": "/usr/local/bin/esl-seqstat",
    "esl-sfetch": "/usr/local/bin/esl-sfetch",
    "esl-shuffle": "/usr/local/bin/esl-shuffle",
    "esl-ssdraw": "/usr/local/bin/esl-ssdraw",
    "esl-translate": "/usr/local/bin/esl-translate",
    "esl-weight": "/usr/local/bin/esl-weight",
    "f2py": "/usr/local/bin/f2py",
    "foldseek": "/usr/local/bin/foldseek",
    "gawk": "/usr/local/bin/gawk",
    "gawk-5.3.1": "/usr/local/bin/gawk-5.3.1",
    "gawkbug": "/usr/local/bin/gawkbug",
    "genbrk": "/usr/local/bin/genbrk",
    "gencfu": "/usr/local/bin/gencfu",
    "gencnval": "/usr/local/bin/gencnval",
    "gendict": "/usr/local/bin/gendict",
    "genrb": "/usr/local/bin/genrb",
    "gsl-config": "/usr/local/bin/gsl-config",
    "gsl-histogram": "/usr/local/bin/gsl-histogram",
    "gsl-randist": "/usr/local/bin/gsl-randist",
    "hf": "/usr/local/bin/hf",
    "hmmalign": "/usr/local/bin/hmmalign",
    "hmmbuild": "/usr/local/bin/hmmbuild",
    "hmmconvert": "/usr/local/bin/hmmconvert",
    "hmmemit": "/usr/local/bin/hmmemit",
    "hmmfetch": "/usr/local/bin/hmmfetch",
    "hmmlogo": "/usr/local/bin/hmmlogo",
    "hmmpgmd": "/usr/local/bin/hmmpgmd",
    "hmmpgmd_shard": "/usr/local/bin/hmmpgmd_shard",
    "hmmpress": "/usr/local/bin/hmmpress",
    "hmmscan": "/usr/local/bin/hmmscan",
    "hmmsearch": "/usr/local/bin/hmmsearch",
    "hmmsim": "/usr/local/bin/hmmsim",
    "hmmstat": "/usr/local/bin/hmmstat",
    "httpx": "/usr/local/bin/httpx",
    "hwloc-annotate": "/usr/local/bin/hwloc-annotate",
    "hwloc-bind": "/usr/local/bin/hwloc-bind",
    "hwloc-calc": "/usr/local/bin/hwloc-calc",
    "hwloc-compress-dir": "/usr/local/bin/hwloc-compress-dir",
    "hwloc-diff": "/usr/local/bin/hwloc-diff",
    "hwloc-distrib": "/usr/local/bin/hwloc-distrib",
    "hwloc-gather-cpuid": "/usr/local/bin/hwloc-gather-cpuid",
    "hwloc-gather-topology": "/usr/local/bin/hwloc-gather-topology",
    "hwloc-info": "/usr/local/bin/hwloc-info",
    "hwloc-ls": "/usr/local/bin/hwloc-ls",
    "hwloc-patch": "/usr/local/bin/hwloc-patch",
    "hwloc-ps": "/usr/local/bin/hwloc-ps",
    "icu-config": "/usr/local/bin/icu-config",
    "icuexportdata": "/usr/local/bin/icuexportdata",
    "icuinfo": "/usr/local/bin/icuinfo",
    "idle3": "/usr/local/bin/idle3",
    "idle3.12": "/usr/local/bin/idle3.12",
    "infocmp": "/usr/local/bin/infocmp",
    "infotocap": "/usr/local/bin/infotocap",
    "isympy": "/usr/local/bin/isympy",
    "jackhmmer": "/usr/local/bin/jackhmmer",
    "lstopo": "/usr/local/bin/lstopo",
    "lstopo-no-graphics": "/usr/local/bin/lstopo-no-graphics",
    "makeconv": "/usr/local/bin/makeconv",
    "makehmmerdb": "/usr/local/bin/makehmmerdb",
    "markdown-it": "/usr/local/bin/markdown-it",
    "mmseqs": "/usr/local/bin/mmseqs",
    "mpiCC": "/usr/local/bin/mpiCC",
    "mpic++": "/usr/local/bin/mpic++",
    "mpicc": "/usr/local/bin/mpicc",
    "mpicxx": "/usr/local/bin/mpicxx",
    "mpiexec": "/usr/local/bin/mpiexec",
    "mpif77": "/usr/local/bin/mpif77",
    "mpif90": "/usr/local/bin/mpif90",
    "mpifort": "/usr/local/bin/mpifort",
    "mpirun": "/usr/local/bin/mpirun",
    "ncurses6-config": "/usr/local/bin/ncurses6-config",
    "ncursesw6-config": "/usr/local/bin/ncursesw6-config",
    "nhmmer": "/usr/local/bin/nhmmer",
    "nhmmscan": "/usr/local/bin/nhmmscan",
    "normalizer": "/usr/local/bin/normalizer",
    "numpy-config": "/usr/local/bin/numpy-config",
    "ompi-clean": "/usr/local/bin/ompi-clean",
    "ompi-server": "/usr/local/bin/ompi-server",
    "ompi_info": "/usr/local/bin/ompi_info",
    "opal_wrapper": "/usr/local/bin/opal_wrapper",
    "openssl": "/usr/local/bin/openssl",
    "orte-clean": "/usr/local/bin/orte-clean",
    "orte-info": "/usr/local/bin/orte-info",
    "orte-server": "/usr/local/bin/orte-server",
    "ortecc": "/usr/local/bin/ortecc",
    "orted": "/usr/local/bin/orted",
    "orterun": "/usr/local/bin/orterun",
    "oshCC": "/usr/local/bin/oshCC",
    "oshc++": "/usr/local/bin/oshc++",
    "oshcc": "/usr/local/bin/oshcc",
    "oshcxx": "/usr/local/bin/oshcxx",
    "oshfort": "/usr/local/bin/oshfort",
    "oshmem_info": "/usr/local/bin/oshmem_info",
    "oshrun": "/usr/local/bin/oshrun",
    "phmmer": "/usr/local/bin/phmmer",
    "pip": "/usr/local/bin/pip",
    "pip3": "/usr/local/bin/pip3",
    "pkgdata": "/usr/local/bin/pkgdata",
    "prodigal": "/usr/local/bin/prodigal",
    "prodigal-gv": "/usr/local/bin/prodigal-gv",
    "profile2mat.pl": "/usr/local/bin/profile2mat.pl",
    "protoc": "/usr/local/bin/protoc",
    "protoc-33.5.0": "/usr/local/bin/protoc-33.5.0",
    "protoc-gen-upb": "/usr/local/bin/protoc-gen-upb",
    "protoc-gen-upb-33.5.0": "/usr/local/bin/protoc-gen-upb-33.5.0",
    "protoc-gen-upb_minitable": "/usr/local/bin/protoc-gen-upb_minitable",
    "protoc-gen-upb_minitable-33.5.0": "/usr/local/bin/protoc-gen-upb_minitable-33.5.0",
    "protoc-gen-upbdefs": "/usr/local/bin/protoc-gen-upbdefs",
    "protoc-gen-upbdefs-33.5.0": "/usr/local/bin/protoc-gen-upbdefs-33.5.0",
    "pybind11-config": "/usr/local/bin/pybind11-config",
    "pydoc": "/usr/local/bin/pydoc",
    "pydoc3": "/usr/local/bin/pydoc3",
    "pydoc3.12": "/usr/local/bin/pydoc3.12",
    "pygmentize": "/usr/local/bin/pygmentize",
    "python": "/usr/local/bin/python",
    "python3": "/usr/local/bin/python3",
    "python3-config": "/usr/local/bin/python3-config",
    "python3.1": "/usr/local/bin/python3.1",
    "python3.12": "/usr/local/bin/python3.12",
    "python3.12-config": "/usr/local/bin/python3.12-config",
    "reset": "/usr/local/bin/reset",
    "shmemCC": "/usr/local/bin/shmemCC",
    "shmemc++": "/usr/local/bin/shmemc++",
    "shmemcc": "/usr/local/bin/shmemcc",
    "shmemcxx": "/usr/local/bin/shmemcxx",
    "shmemfort": "/usr/local/bin/shmemfort",
    "shmemrun": "/usr/local/bin/shmemrun",
    "spm_decode": "/usr/local/bin/spm_decode",
    "spm_encode": "/usr/local/bin/spm_encode",
    "spm_export_vocab": "/usr/local/bin/spm_export_vocab",
    "spm_normalize": "/usr/local/bin/spm_normalize",
    "spm_train": "/usr/local/bin/spm_train",
    "sqlite3_analyzer": "/usr/local/bin/sqlite3_analyzer",
    "tabs": "/usr/local/bin/tabs",
    "tafinder": "/usr/local/bin/tafinder",
    "tclsh": "/usr/local/bin/tclsh",
    "tclsh8.6": "/usr/local/bin/tclsh8.6",
    "tic": "/usr/local/bin/tic",
    "tiny-agents": "/usr/local/bin/tiny-agents",
    "toe": "/usr/local/bin/toe",
    "torch_shm_manager": "/usr/local/bin/torch_shm_manager",
    "torchfrtrace": "/usr/local/bin/torchfrtrace",
    "torchrun": "/usr/local/bin/torchrun",
    "tput": "/usr/local/bin/tput",
    "tqdm": "/usr/local/bin/tqdm",
    "transformers": "/usr/local/bin/transformers",
    "tset": "/usr/local/bin/tset",
    "typer": "/usr/local/bin/typer",
    "unzstd": "/usr/local/bin/unzstd",
    "wheel": "/usr/local/bin/wheel",
    "wish": "/usr/local/bin/wish",
    "wish8.6": "/usr/local/bin/wish8.6",
    "x86_64-conda-linux-gnu-ld": "/usr/local/bin/x86_64-conda-linux-gnu-ld",
    "xml2-config": "/usr/local/bin/xml2-config",
    "xmlcatalog": "/usr/local/bin/xmlcatalog",
    "xmllint": "/usr/local/bin/xmllint",
    "zstd": "/usr/local/bin/zstd",
    "zstdcat": "/usr/local/bin/zstdcat",
    "zstdgrep": "/usr/local/bin/zstdgrep",
    "zstdless": "/usr/local/bin/zstdless",
    "zstdmt": "/usr/local/bin/zstdmt"
}